{"status": "ok", "table": {"rows": [{"c": [{"v": "US-GA"}, {"f": "100", "v": 100.0}, {"v": "#geo=US-GA&q=number"}, {"v": ""}]}, {"c": [{"v": "US-MS"}, {"f": "98", "v": 98.0}, {"v": "#geo=US-MS&q=number"}, {"v": ""}]}, {"c": [{"v": "US-WV"}, {"f": "95", "v": 95.0}, {"v": "#geo=US-WV&q=number"}, {"v": ""}]}, {"c": [{"v": "US-SC"}, {"f": "94", "v": 94.0}, {"v": "#geo=US-SC&q=number"}, {"v": ""}]}, {"c": [{"v": "US-FL"}, {"f": "93", "v": 93.0}, {"v": "#geo=US-FL&q=number"}, {"v": ""}]}, {"c": [{"v": "US-DC"}, {"f": "92", "v": 92.0}, {"v": "#geo=US-DC&q=number"}, {"v": ""}]}, {"c": [{"v": "US-AR"}, {"f": "91", "v": 91.0}, {"v": "#geo=US-AR&q=number"}, {"v": ""}]}, {"c": [{"v": "US-IL"}, {"f": "91", "v": 91.0}, {"v": "#geo=US-IL&q=number"}, {"v": ""}]}, {"c": [{"v": "US-TN"}, {"f": "91", "v": 91.0}, {"v": "#geo=US-TN&q=number"}, {"v": ""}]}, {"c": [{"v": "US-MI"}, {"f": "90", "v": 90.0}, {"v": "#geo=US-MI&q=number"}, {"v": ""}]}, {"c": [{"v": "US-TX"}, {"f": "88", "v": 88.0}, {"v": "#geo=US-TX&q=number"}, {"v": ""}]}, {"c": [{"v": "US-NC"}, {"f": "88", "v": 88.0}, {"v": "#geo=US-NC&q=number"}, {"v": ""}]}, {"c": [{"v": "US-MO"}, {"f": "88", "v": 88.0}, {"v": "#geo=US-MO&q=number"}, {"v": ""}]}, {"c": [{"v": "US-KY"}, {"f": "88", "v": 88.0}, {"v": "#geo=US-KY&q=number"}, {"v": ""}]}, {"c": [{"v": "US-LA"}, {"f": "86", "v": 86.0}, {"v": "#geo=US-LA&q=number"}, {"v": ""}]}, {"c": [{"v": "US-AL"}, {"f": "84", "v": 84.0}, {"v": "#geo=US-AL&q=number"}, {"v": ""}]}, {"c": [{"v": "US-IN"}, {"f": "84", "v": 84.0}, {"v": "#geo=US-IN&q=number"}, {"v": ""}]}, {"c": [{"v": "US-OK"}, {"f": "84", "v": 84.0}, {"v": "#geo=US-OK&q=number"}, {"v": ""}]}, {"c": [{"v": "US-OH"}, {"f": "84", "v": 84.0}, {"v": "#geo=US-OH&q=number"}, {"v": ""}]}, {"c": [{"v": "US-NV"}, {"f": "84", "v": 84.0}, {"v": "#geo=US-NV&q=number"}, {"v": ""}]}, {"c": [{"v": "US-PA"}, {"f": "84", "v": 84.0}, {"v": "#geo=US-PA&q=number"}, {"v": ""}]}, {"c": [{"v": "US-NE"}, {"f": "83", "v": 83.0}, {"v": "#geo=US-NE&q=number"}, {"v": ""}]}, {"c": [{"v": "US-AZ"}, {"f": "83", "v": 83.0}, {"v": "#geo=US-AZ&q=number"}, {"v": ""}]}, {"c": [{"v": "US-MA"}, {"f": "82", "v": 82.0}, {"v": "#geo=US-MA&q=number"}, {"v": ""}]}, {"c": [{"v": "US-NY"}, {"f": "82", "v": 82.0}, {"v": "#geo=US-NY&q=number"}, {"v": ""}]}, {"c": [{"v": "US-MD"}, {"f": "82", "v": 82.0}, {"v": "#geo=US-MD&q=number"}, {"v": ""}]}, {"c": [{"v": "US-DE"}, {"f": "82", "v": 82.0}, {"v": "#geo=US-DE&q=number"}, {"v": ""}]}, {"c": [{"v": "US-UT"}, {"f": "80", "v": 80.0}, {"v": "#geo=US-UT&q=number"}, {"v": ""}]}, {"c": [{"v": "US-MN"}, {"f": "80", "v": 80.0}, {"v": "#geo=US-MN&q=number"}, {"v": ""}]}, {"c": [{"v": "US-CO"}, {"f": "79", "v": 79.0}, {"v": "#geo=US-CO&q=number"}, {"v": ""}]}, {"c": [{"v": "US-IA"}, {"f": "79", "v": 79.0}, {"v": "#geo=US-IA&q=number"}, {"v": ""}]}, {"c": [{"v": "US-KS"}, {"f": "78", "v": 78.0}, {"v": "#geo=US-KS&q=number"}, {"v": ""}]}, {"c": [{"v": "US-NJ"}, {"f": "77", "v": 77.0}, {"v": "#geo=US-NJ&q=number"}, {"v": ""}]}, {"c": [{"v": "US-ID"}, {"f": "77", "v": 77.0}, {"v": "#geo=US-ID&q=number"}, {"v": ""}]}, {"c": [{"v": "US-WI"}, {"f": "76", "v": 76.0}, {"v": "#geo=US-WI&q=number"}, {"v": ""}]}, {"c": [{"v": "US-NM"}, {"f": "76", "v": 76.0}, {"v": "#geo=US-NM&q=number"}, {"v": ""}]}, {"c": [{"v": "US-AK"}, {"f": "76", "v": 76.0}, {"v": "#geo=US-AK&q=number"}, {"v": ""}]}, {"c": [{"v": "US-ND"}, {"f": "75", "v": 75.0}, {"v": "#geo=US-ND&q=number"}, {"v": ""}]}, {"c": [{"v": "US-CT"}, {"f": "74", "v": 74.0}, {"v": "#geo=US-CT&q=number"}, {"v": ""}]}, {"c": [{"v": "US-RI"}, {"f": "74", "v": 74.0}, {"v": "#geo=US-RI&q=number"}, {"v": ""}]}, {"c": [{"v": "US-SD"}, {"f": "74", "v": 74.0}, {"v": "#geo=US-SD&q=number"}, {"v": ""}]}, {"c": [{"v": "US-HI"}, {"f": "74", "v": 74.0}, {"v": "#geo=US-HI&q=number"}, {"v": ""}]}, {"c": [{"v": "US-CA"}, {"f": "73", "v": 73.0}, {"v": "#geo=US-CA&q=number"}, {"v": ""}]}, {"c": [{"v": "US-WA"}, {"f": "73", "v": 73.0}, {"v": "#geo=US-WA&q=number"}, {"v": ""}]}, {"c": [{"v": "US-MT"}, {"f": "72", "v": 72.0}, {"v": "#geo=US-MT&q=number"}, {"v": ""}]}, {"c": [{"v": "US-WY"}, {"f": "71", "v": 71.0}, {"v": "#geo=US-WY&q=number"}, {"v": ""}]}, {"c": [{"v": "US-NH"}, {"f": "69", "v": 69.0}, {"v": "#geo=US-NH&q=number"}, {"v": ""}]}, {"c": [{"v": "US-VT"}, {"f": "69", "v": 69.0}, {"v": "#geo=US-VT&q=number"}, {"v": ""}]}, {"c": [{"v": "US-ME"}, {"f": "69", "v": 69.0}, {"v": "#geo=US-ME&q=number"}, {"v": ""}]}, {"c": [{"v": "US-VA"}, {"f": "66", "v": 66.0}, {"v": "#geo=US-VA&q=number"}, {"v": ""}]}, {"c": [{"v": "US-OR"}, {"f": "51", "v": 51.0}, {"v": "#geo=US-OR&q=number"}, {"v": ""}]}], "cols": [{"pattern": "", "type": "string", "id": "query", "label": "Query"}, {"pattern": "", "type": "number", "id": "amount", "label": "Amount"}, {"pattern": "", "type": "string", "id": "internalUrl", "label": "Product URL"}, {"pattern": "", "type": "string", "id": "externalUrl", "label": "Search URL"}]}, "version": "0.6", "sig": "433235395"}